crawlframe/__init__.py
crawlframe/__main__.py
crawlframe/__version__.py
crawlframe/cmd.py
crawlframe/commands/__init__.py
crawlframe/commands/createapp.py
crawlframe/commands/createpro.py
crawlframe/commands/reloads.py
crawlframe/commands/restarts.py
crawlframe/commands/starts.py
crawlframe/commands/stops.py
crawlframe/configs/__init__.py
crawlframe/configs/default_settings.py
crawlframe/cores/__init__.py
crawlframe/cores/crawlers/__init__.py
crawlframe/cores/downloader/__init__.py
crawlframe/cores/downloader/download.py
crawlframe/cores/middlewares/__init__.py
crawlframe/cores/middlewares/request.py
crawlframe/cores/middlewares/response.py
crawlframe/cores/middlewares/spider.py
crawlframe/cores/models/__init__.py
crawlframe/cores/models/cache.py
crawlframe/cores/models/connection.py
crawlframe/cores/models/database.py
crawlframe/cores/parsers/__init__.py
crawlframe/cores/parsers/parcel.py
crawlframe/cores/parsers/parser.py
crawlframe/cores/requests/__init__.py
crawlframe/cores/requests/requester.py
crawlframe/cores/requests/response.py
crawlframe/engine/__init__.py
crawlframe/engine/crawl.py
crawlframe/engine/spiders_container.py
crawlframe/templates/__init__.py
crawlframe/templates/app/__init__.py
crawlframe/templates/app/manage.py
crawlframe/templates/projects/__init__.py
crawlframe/templates/projects/manage.py
crawlframe/templates/projects/apps/__init__.py
crawlframe/templates/projects/settings/__init__.py
crawlframe/templates/projects/settings/default.py
crawlframe/templates/projects/settings/dev.py
crawlframe/templates/projects/settings/pro.py
crawlframe/utils/__init__.py
crawlframe/utils/errors.py
crawlframe/utils/logger.py
crawlframe/utils/middle.py
crawlframe/utils/pools.py
crawlframe/utils/queues.py
crawlframe/utils/reload_module.py
crawlframe/utils/signals.py
crawlframe/utils/timers.py
crawlframe-1.0.3.dist-info/LICENSE
crawlframe-1.0.3.dist-info/METADATA
crawlframe-1.0.3.dist-info/WHEEL
crawlframe-1.0.3.dist-info/entry_points.txt
crawlframe-1.0.3.dist-info/top_level.txt
crawlframe-1.0.3.dist-info/RECORD
